docs/AI_README.md
docs/__init__.py
docs/cookbook.md
docs/examples/__init__.py
docs/examples/basic_vbbk.py
docs/examples/dp_server_with_metric.py
docs/examples/dp_supertask.py
docs/examples/first_workflow.py
docs/examples/getting_started.py
docs/examples/ai/IntelImageClassification.py
docs/examples/ai/MnistModel.py
docs/examples/ai/MyEncodeDecodeModel.py
docs/examples/ai/MyKerasModel.py
docs/examples/ai/MyTrackerModel.py
docs/examples/ai/__init__.py
docs/examples/llm/README.md
docs/examples/llm/local_input_data/Legal-Document.jpg
docs/examples/llm/local_input_data/invoice.png
docs/images/graphql_endpoint.png
superai/__init__.py
superai/client.py
superai/config.py
superai/exceptions.py
superai/settings.yaml
superai/version.py
superai/apis/__init__.py
superai/apis/auth.py
superai/apis/data.py
superai/apis/data_program.py
superai/apis/ground_truth.py
superai/apis/jobs.py
superai/apis/operations.py
superai/apis/project.py
superai/apis/super_task.py
superai/apis/task_instance.py
superai/apis/task_template.py
superai/apis/tasks.py
superai/apis/workflow.py
superai/apis/meta_ai/__init__.py
superai/apis/meta_ai/ai.py
superai/apis/meta_ai/base.py
superai/apis/meta_ai/checkpoint.py
superai/apis/meta_ai/instance.py
superai/apis/meta_ai/meta_ai_graphql_schema.py
superai/apis/meta_ai/model.py
superai/apis/meta_ai/patch_schema.py
superai/apis/meta_ai/project_ai.py
superai/apis/meta_ai/session.py
superai/cli/__init__.py
superai/cli/ai.py
superai/cli/ai_instance.py
superai/cli/ai_methods.py
superai/cli/ai_training.py
superai/cli/config.py
superai/cli/helper.py
superai/cli/misc.py
superai/data_program/Exceptions.py
superai/data_program/__init__.py
superai/data_program/base.py
superai/data_program/data_program.py
superai/data_program/dp_server.py
superai/data_program/project.py
superai/data_program/types.py
superai/data_program/utils.py
superai/data_program/combiner/__init__.py
superai/data_program/combiner/agreement_scores.py
superai/data_program/combiner/combiner_functions.py
superai-0.3.0.dist-info/LICENSE
superai-0.3.0.dist-info/METADATA
superai-0.3.0.dist-info/WHEEL
superai-0.3.0.dist-info/entry_points.txt
superai-0.3.0.dist-info/top_level.txt
superai-0.3.0.dist-info/RECORD
