Metadata-Version: 2.1
Name: superai
Version: 0.3.0
Summary: super.AI API
Home-page: https://github.com/mysuperai/superai-sdk
Author: super.AI
Author-email: support@super.ai
Keywords: super.AI API,super.AI SDK
License-File: LICENSE
Requires-Dist: attrs >=22.1.0
Requires-Dist: awesome-pattern-matching >=0.22.0
Requires-Dist: boto3 >=1.15
Requires-Dist: click >=7.0
Requires-Dist: diskcache >=5.4.0
Requires-Dist: dynaconf >=3.1.12
Requires-Dist: fastapi <0.104.0,>=0.70.0
Requires-Dist: futures-then >=0.1.1
Requires-Dist: genson >=1.2.2
Requires-Dist: jinja2 >=2.11.2
Requires-Dist: joblib >=0.17.0
Requires-Dist: jsonmerge >=1.7.0
Requires-Dist: jsonpickle >=1.4.1
Requires-Dist: pandas >=1.2.5
Requires-Dist: pip >=19.1
Requires-Dist: pycognito >=2022.12.0
Requires-Dist: pydantic <2.0.0
Requires-Dist: pyyaml >=3.13
Requires-Dist: requests >=2.22
Requires-Dist: rich >=10.1
Requires-Dist: scikit-learn >=0.23.2
Requires-Dist: sentry-sdk >=0.19.4
Requires-Dist: sgqlc[websocket] >=16.2
Requires-Dist: uvicorn >=0.15.0
Requires-Dist: superai-logging >=0.1.0
Requires-Dist: opentelemetry-distro[otlp] >=0.40b0
Requires-Dist: opentelemetry-instrumentation-botocore >=0.40b0
Requires-Dist: opentelemetry-instrumentation-requests >=0.40b0
Requires-Dist: opentelemetry-instrumentation-fastapi >=0.40b0
Provides-Extra: ai
Requires-Dist: docker >=5.0.0 ; extra == 'ai'
Requires-Dist: polyaxon >=1.14.3 ; extra == 'ai'
Requires-Dist: protobuf <4,>=3.20.1 ; extra == 'ai'
Requires-Dist: netifaces >=0.11.0 ; extra == 'ai'
Requires-Dist: jsonlines >=4.0.0 ; extra == 'ai'
Requires-Dist: superai-builder >=0.9.1 ; extra == 'ai'
Requires-Dist: pydantic <2,>=1.8.2 ; extra == 'ai'
Requires-Dist: superai-dataclient ~=0.1.0 ; extra == 'ai'
Requires-Dist: superai-schema ~=0.7 ; extra == 'ai'
Provides-Extra: build
Requires-Dist: pyngrok >=6.0.0 ; extra == 'build'
Requires-Dist: superai-transport >=1.0.16 ; extra == 'build'
Requires-Dist: Sphinx >=3.2.1 ; extra == 'build'
Requires-Dist: black ; extra == 'build'
Requires-Dist: bump2version >=1.0.0 ; extra == 'build'
Requires-Dist: setuptools >=50.3.2 ; extra == 'build'
Requires-Dist: twine >=3.2.0 ; extra == 'build'
Requires-Dist: wheel >=0.35.1 ; extra == 'build'
Requires-Dist: superai-dataclient ~=0.1.0 ; extra == 'build'
Requires-Dist: superai-schema ~=0.7 ; extra == 'build'
Requires-Dist: pydantic <2,>=1.8.2 ; extra == 'build'
Provides-Extra: complete
Requires-Dist: Sphinx >=3.2.1 ; extra == 'complete'
Requires-Dist: black ; extra == 'complete'
Requires-Dist: bump2version >=1.0.0 ; extra == 'complete'
Requires-Dist: setuptools >=50.3.2 ; extra == 'complete'
Requires-Dist: twine >=3.2.0 ; extra == 'complete'
Requires-Dist: wheel >=0.35.1 ; extra == 'complete'
Requires-Dist: pyngrok >=6.0.0 ; extra == 'complete'
Requires-Dist: superai-transport >=1.0.16 ; extra == 'complete'
Requires-Dist: docker >=5.0.0 ; extra == 'complete'
Requires-Dist: polyaxon >=1.14.3 ; extra == 'complete'
Requires-Dist: protobuf <4,>=3.20.1 ; extra == 'complete'
Requires-Dist: netifaces >=0.11.0 ; extra == 'complete'
Requires-Dist: jsonlines >=4.0.0 ; extra == 'complete'
Requires-Dist: superai-builder >=0.9.1 ; extra == 'complete'
Requires-Dist: pydantic <2,>=1.8.2 ; extra == 'complete'
Requires-Dist: tabulate ~=0.9.0 ; extra == 'complete'
Requires-Dist: tiktoken ~=0.4.0 ; extra == 'complete'
Requires-Dist: openai ~=1.6.1 ; extra == 'complete'
Requires-Dist: shapely >=2.0.2 ; extra == 'complete'
Requires-Dist: coverage >=5.3 ; extra == 'complete'
Requires-Dist: deepdiff >=4.0.7 ; extra == 'complete'
Requires-Dist: dictdiffer >=0.9.0 ; extra == 'complete'
Requires-Dist: moto >=5 ; extra == 'complete'
Requires-Dist: pytest-cov >=2.10.1 ; extra == 'complete'
Requires-Dist: pytest-env >=0.6.2 ; extra == 'complete'
Requires-Dist: pytest-mock ~=3.12.0 ; extra == 'complete'
Requires-Dist: pytest-vcr >=1.0.2 ; extra == 'complete'
Requires-Dist: pytest-httpserver >=1.0.8 ; extra == 'complete'
Requires-Dist: pytest <8,>=6.1.2 ; extra == 'complete'
Requires-Dist: tox >=2.9.1 ; extra == 'complete'
Requires-Dist: vcrpy >=4.1.1 ; extra == 'complete'
Requires-Dist: httpx ~=0.25.1 ; extra == 'complete'
Requires-Dist: superai-dataclient ~=0.1.0 ; extra == 'complete'
Requires-Dist: superai-schema ~=0.7 ; extra == 'complete'
Provides-Extra: dp
Requires-Dist: pyngrok >=6.0.0 ; extra == 'dp'
Requires-Dist: superai-transport >=1.0.16 ; extra == 'dp'
Requires-Dist: superai-dataclient ~=0.1.0 ; extra == 'dp'
Requires-Dist: superai-schema ~=0.7 ; extra == 'dp'
Requires-Dist: pydantic <2,>=1.8.2 ; extra == 'dp'
Provides-Extra: llm
Requires-Dist: tabulate ~=0.9.0 ; extra == 'llm'
Requires-Dist: tiktoken ~=0.4.0 ; extra == 'llm'
Requires-Dist: openai ~=1.6.1 ; extra == 'llm'
Requires-Dist: shapely >=2.0.2 ; extra == 'llm'
Requires-Dist: docker >=5.0.0 ; extra == 'llm'
Requires-Dist: polyaxon >=1.14.3 ; extra == 'llm'
Requires-Dist: protobuf <4,>=3.20.1 ; extra == 'llm'
Requires-Dist: netifaces >=0.11.0 ; extra == 'llm'
Requires-Dist: jsonlines >=4.0.0 ; extra == 'llm'
Requires-Dist: superai-builder >=0.9.1 ; extra == 'llm'
Requires-Dist: pydantic <2,>=1.8.2 ; extra == 'llm'
Requires-Dist: pyngrok >=6.0.0 ; extra == 'llm'
Requires-Dist: superai-transport >=1.0.16 ; extra == 'llm'
Requires-Dist: superai-dataclient ~=0.1.0 ; extra == 'llm'
Requires-Dist: superai-schema ~=0.7 ; extra == 'llm'
Provides-Extra: test
Requires-Dist: tabulate ~=0.9.0 ; extra == 'test'
Requires-Dist: tiktoken ~=0.4.0 ; extra == 'test'
Requires-Dist: openai ~=1.6.1 ; extra == 'test'
Requires-Dist: shapely >=2.0.2 ; extra == 'test'
Requires-Dist: coverage >=5.3 ; extra == 'test'
Requires-Dist: deepdiff >=4.0.7 ; extra == 'test'
Requires-Dist: dictdiffer >=0.9.0 ; extra == 'test'
Requires-Dist: moto >=5 ; extra == 'test'
Requires-Dist: pytest-cov >=2.10.1 ; extra == 'test'
Requires-Dist: pytest-env >=0.6.2 ; extra == 'test'
Requires-Dist: pytest-mock ~=3.12.0 ; extra == 'test'
Requires-Dist: pytest-vcr >=1.0.2 ; extra == 'test'
Requires-Dist: pytest-httpserver >=1.0.8 ; extra == 'test'
Requires-Dist: pytest <8,>=6.1.2 ; extra == 'test'
Requires-Dist: superai-builder >=0.9.1 ; extra == 'test'
Requires-Dist: tox >=2.9.1 ; extra == 'test'
Requires-Dist: vcrpy >=4.1.1 ; extra == 'test'
Requires-Dist: httpx ~=0.25.1 ; extra == 'test'
Requires-Dist: pyngrok >=6.0.0 ; extra == 'test'
Requires-Dist: superai-transport >=1.0.16 ; extra == 'test'
Requires-Dist: docker >=5.0.0 ; extra == 'test'
Requires-Dist: polyaxon >=1.14.3 ; extra == 'test'
Requires-Dist: protobuf <4,>=3.20.1 ; extra == 'test'
Requires-Dist: netifaces >=0.11.0 ; extra == 'test'
Requires-Dist: jsonlines >=4.0.0 ; extra == 'test'
Requires-Dist: pydantic <2,>=1.8.2 ; extra == 'test'
Requires-Dist: superai-dataclient ~=0.1.0 ; extra == 'test'
Requires-Dist: superai-schema ~=0.7 ; extra == 'test'
